<?xml version="1.0" ?><annotation>
    <folder>VOC2007</folder>
    <filename>1606.jpg</filename>
<source>
<database>orgaquant</database>
<annotation>organoids</annotation>
</source>
    <size>
        <width>450</width>
        <height>269</height>
        <depth>3</depth>
    </size>
    <object>
<name>Broken hole</name>
        <bndbox>
            <xmin>126</xmin>
            <ymin>65</ymin>
            <xmax>138</xmax>
            <ymax>77</ymax>
        </bndbox>
    </object>
    <object>
<name>Broken hole</name>
        <bndbox>
            <xmin>135</xmin>
            <ymin>127</ymin>
            <xmax>148</xmax>
            <ymax>139</ymax>
        </bndbox>
    </object>
</annotation>