<?xml version="1.0" ?><annotation>
    <folder>VOC2007</folder>
    <filename>366.jpg</filename>
<source>
<database>orgaquant</database>
<annotation>organoids</annotation>
</source>
    <size>
        <width>450</width>
        <height>269</height>
        <depth>3</depth>
    </size>
    <object>
<name>Oblique printing</name>
        <bndbox>
            <xmin>423</xmin>
            <ymin>197</ymin>
            <xmax>434</xmax>
            <ymax>213</ymax>
        </bndbox>
    </object>
</annotation>